setup.cfg
setup.py
dm/__init__.py
dm/compat.py
dm/tests.py
dm.egg-info/PKG-INFO
dm.egg-info/SOURCES.txt
dm.egg-info/dependency_links.txt
dm.egg-info/not-zip-safe
dm.egg-info/top_level.txt