Metadata-Version: 1.0
Name: dm
Version: 1.1dev
Summary: Dict to Data mapper
Home-page: UNKNOWN
Author: Bence Faludi
Author-email: b.faludi@mito.hu
License: GPL
Platform: UNKNOWN
